promethee_roc/__init__.py
promethee_roc/algoritmo/__init__.py
promethee_roc/algoritmo/main.py
promethee_roc/algoritmo/output.py
promethee_roc/algoritmo/promethee.py
promethee_ROC-1.0.0.dist-info/METADATA
promethee_ROC-1.0.0.dist-info/WHEEL
promethee_ROC-1.0.0.dist-info/top_level.txt
promethee_ROC-1.0.0.dist-info/RECORD
